oss_api/__init__.py
oss_api/authentication.py
oss_api/c.py
oss_api/cS.py
oss_api/rL.py
oss_api/rS.py
oss_api/uL.py
oss_api-0.0.4.data/scripts/oss.bat
oss_api-0.0.4.data/scripts/oss.py
oss_api-0.0.4.dist-info/METADATA
oss_api-0.0.4.dist-info/WHEEL
oss_api-0.0.4.dist-info/top_level.txt
oss_api-0.0.4.dist-info/RECORD
