Metadata-Version: 2.1
Name: oss-api
Version: 0.0.4
Summary: api for IMDC's OSS server
Home-page: https://gitlab.com/imdc/packages/oss_api
Author: kdd
Author-email: kdd@imdc.be
License: UNKNOWN
Platform: UNKNOWN
Classifier: Programming Language :: Python
Classifier: Programming Language :: Python :: 3
Classifier: Programming Language :: Python :: 2.7
Requires-Dist: requests
